rtxpy/__init__.py
rtxpy/rtx.py
rtxpy/rtxpy.dll
rtxpy/tests/__init__.py
rtxpy/tests/test_simple.py
rtxpy-0.0.3.dist-info/LICENSE
rtxpy-0.0.3.dist-info/METADATA
rtxpy-0.0.3.dist-info/WHEEL
rtxpy-0.0.3.dist-info/top_level.txt
rtxpy-0.0.3.dist-info/RECORD
